pardata/__init__.py
pardata/_config.py
pardata/_dataset.py
pardata/_high_level.py
pardata/_lock.py
pardata/_schema.py
pardata/_schema_retrieval.py
pardata/_typing.py
pardata/_version.py
pardata/dataset.py
pardata/exceptions.py
pardata/schema.py
pardata/typing.py
pardata/loaders/__init__.py
pardata/loaders/_audio.py
pardata/loaders/_base.py
pardata/loaders/_format_loader_map.py
pardata/loaders/_image.py
pardata/loaders/_table.py
pardata/loaders/_text.py
pardata/loaders/audio.py
pardata/loaders/image.py
pardata/loaders/table.py
pardata/loaders/text.py
pardata-0.4.0.data/data/LICENSE
pardata-0.4.0.dist-info/AUTHORS.rst
pardata-0.4.0.dist-info/LICENSE
pardata-0.4.0.dist-info/METADATA
pardata-0.4.0.dist-info/WHEEL
pardata-0.4.0.dist-info/top_level.txt
pardata-0.4.0.dist-info/RECORD
