Metadata-Version: 2.1
Name: pardata
Version: 0.4.0
Summary: A Python API that enables data consumers and distributors to easily use and share datasets, and establishes a standard for exchanging data assets.
Home-page: UNKNOWN
Author: IBM Center for Open Source Data and AI Technologies (CODAIT)
License: Apache v2
Keywords: machine-learning data-mining data-science
Platform: UNKNOWN
Classifier: Development Status :: 4 - Beta
Classifier: Intended Audience :: Developers
Classifier: License :: OSI Approved :: Apache Software License
Classifier: Operating System :: OS Independent
Classifier: Programming Language :: Python
Classifier: Programming Language :: Python :: 3
Classifier: Programming Language :: Python :: 3.6
Classifier: Programming Language :: Python :: 3.7
Classifier: Programming Language :: Python :: 3.8
Classifier: Programming Language :: Python :: 3.9
Classifier: Programming Language :: Python :: 3 :: Only
Classifier: Programming Language :: Python :: Implementation :: CPython
Classifier: Programming Language :: Python :: Implementation :: PyPy
Classifier: Topic :: Scientific/Engineering
Classifier: Topic :: Software Development :: Libraries
Requires-Python: >=3.6
License-File: LICENSE
License-File: AUTHORS.rst
Requires-Dist: packaging (>=20.4)
Requires-Dist: pandas (>=1.1.0)
Requires-Dist: Pillow (>=8.2.0)
Requires-Dist: pydantic (>=1.7.2)
Requires-Dist: PyYAML (>=5.3.1)
Requires-Dist: requests (>=2.24.0)
Requires-Dist: dataclasses ; python_version < "3.7.0"
